Workbook

Sheet 说明
A1: HBM 供需模型 v0.4（2026-10-15，由 hbm/build.py 生成，勿手改）
A2: 黄色格=可改假设；其余为公式。1 EB = 10 亿 GB。
A3: 需求 = 出货（百万颗）× 每封装 HBM（GB），与 CoWoS 页共用 KGI 出货表
A4: 供给 = 年均月投片（千片）× 12 × 每片有效 GB × 稼动率
A5: 每片有效 GB 不是原厂披露值，而是用券商汇总的产量反推：2025 年 iM 证券称业界产量 26.3 亿 GB、2026 年预计 44.4 亿 GB [源65]；用 UBS 年末产能 [源63]插值得到的年均投片去除，得到 2025 年约 750、2026 年约 880 GB/片（稼动率 85%/90%，估）。2027 年 HBM4/4E die 更大、16 层良率更低 [源1]，先按与 2026 年持平处理。旧版 600/650/600 是"让 2026 年供需接近平衡"倒推的，加上产能锚点偏低，2026 年供给少算了约三分之一（2.9 对 4.4 EB）。

Sheet 需求
A1: 年份 | B1: 厂商 | C1: 芯片 | D1: 出货(百万) | E1: 每封装HBM(GB) | F1: 需求(PB) | G1: 来源
A2: 2023 | B2: 英伟达 | C2: 英伟达 A100 | D2: 1.45 | E2: 80 | F2: =D2*E2 | G2: KGI Fig.10（经 CoWoS 页）
A3: 2023 | B3: AMD | C3: AMD MI250/MI300 | D3: 0.168 | E3: 128 | F3: =D3*E3 | G3: KGI Fig.10（经 CoWoS 页）
A4: 2023 | B4: 其他/中国 | C4: 其他GPU Gaudi等 | D4: 0.027 | E4: 96 | F4: =D4*E4 | G4: KGI Fig.10（经 CoWoS 页）
A5: 2023 | B5: 谷歌TPU | C5: 谷歌TPU TPU v4/v5 | D5: 1.464 | E5: 32 | F5: =D5*E5 | G5: KGI Fig.10（经 CoWoS 页）
A6: 2023 | B6: AWS | C6: AWS Trainium1/Inferentia2 | D6: 0.495 | E6: 32 | F6: =D6*E6 | G6: KGI Fig.10（经 CoWoS 页）
A7: 2023 | B7: 其他/中国 | C7: 其他ASIC 其他 | D7: 0.3 | E7: 32 | F7: =D7*E7 | G7: KGI Fig.10（经 CoWoS 页）
A8: 2024 | B8: 英伟达 | C8: 英伟达 A100 | D8: 0.088 | E8: 80 | F8: =D8*E8 | G8: KGI Fig.10（经 CoWoS 页）
A9: 2024 | B9: 英伟达 | C9: 英伟达 H100/H200 | D9: 3.218 | E9: 90 | F9: =D9*E9 | G9: KGI Fig.10（经 CoWoS 页）
A10: 2024 | B10: 英伟达 | C10: 英伟达 B200 | D10: 0.532 | E10: 192 | F10: =D10*E10 | G10: KGI Fig.10（经 CoWoS 页）
A11: 2024 | B11: AMD | C11: AMD MI300X | D11: 0.49 | E11: 192 | F11: =D11*E11 | G11: KGI Fig.10（经 CoWoS 页）
A12: 2024 | B12: 其他/中国 | C12: 其他GPU Gaudi/其他 | D12: 0.402 | E12: 96 | F12: =D12*E12 | G12: KGI Fig.10（经 CoWoS 页）
A13: 2024 | B13: 谷歌TPU | C13: 谷歌TPU TPU v5/v6 | D13: 2.099 | E13: 40 | F13: =D13*E13 | G13: KGI Fig.10（经 CoWoS 页）
... A43: 2027 | B43: 其他/中国 | C43: 其他ASIC Maia/MTIA/OpenAI/其他 | D43: 2.3 | E43: 200 | F43: =D43*E43 | G43: KGI Fig.10（经 CoWoS 页）

Sheet 供给
A1: 年份 | B1: 厂商 | C1: 年均月投片(千片) | D1: 每片有效GB | E1: 稼动率 | F1: 年供给(PB)
A2: 2025 | B2: SK hynix | C2: 160 | D2: 750 | E2: 0.85 | F2: =C2*12*D2*E2/1000
A3: 2025 | B3: Samsung | C3: 136.9 | D3: 750 | E3: 0.85 | F3: =C3*12*D3*E3/1000
A4: 2025 | B4: Micron | C4: 51.9 | D4: 750 | E4: 0.85 | F4: =C4*12*D4*E4/1000
A5: 2026 | B5: SK hynix | C5: 209.4 | D5: 880 | E5: 0.9 | F5: =C5*12*D5*E5/1000
A6: 2026 | B6: Samsung | C6: 162.5 | D6: 880 | E6: 0.9 | F6: =C6*12*D6*E6/1000
A7: 2026 | B7: Micron | C7: 86.9 | D7: 880 | E7: 0.9 | F7: =C7*12*D7*E7/1000
A8: 2027 | B8: SK hynix | C8: 255 | D8: 880 | E8: 0.9 | F8: =C8*12*D8*E8/1000
A9: 2027 | B9: Samsung | C9: 226.2 | D9: 880 | E9: 0.9 | F9: =C9*12*D9*E9/1000
A10: 2027 | B10: Micron | C10: 137.5 | D10: 880 | E10: 0.9 | F10: =C10*12*D10*E10/1000

Sheet 季度产能
A1: 季度 | B1: 类型 | C1: SK hynix | D1: Samsung | E1: Micron | F1: CXMT
A2: 1Q23 | B2: 图读数 | C2: 15 | D2: 15 | E2: 4 | F2: 0
A3: 2Q23 | B3: 图读数 | C3: 20 | D3: 20 | E3: 4 | F3: 0
A4: 3Q23 | B4: 图读数 | C4: 35 | D4: 35 | E4: 4 | F4: 0
A5: 4Q23 | B5: 图读数 | C5: 45 | D5: 45 | E5: 4 | F5: 0
A6: 1Q24 | B6: 图读数 | C6: 60 | D6: 45 | E6: 10 | F6: 0
A7: 2Q24 | B7: 图读数 | C7: 80 | D7: 45 | E7: 15 | F7: 0
A8: 3Q24 | B8: 图读数 | C8: 110 | D8: 80 | E8: 25 | F8: 0
A9: 4Q24 | B9: 图读数 | C9: 135 | D9: 115 | E9: 30 | F9: 0
A10: 1Q25 | B10: 插值 | C10: 145 | D10: 123.8 | E10: 38.8 | F10: 0
A11: 2Q25 | B11: 插值 | C11: 155 | D11: 132.5 | E11: 47.5 | F11: 0
A12: 3Q25 | B12: 插值 | C12: 165 | D12: 141.2 | E12: 56.2 | F12: 0
A13: 4Q25 | B13: 锚点 | C13: 175 | D13: 150 | E13: 65 | F13: 0
... A21: 4Q27 | B21: 锚点 | C21: 270 | D21: 260 | E21: 160 | F21: 25

Sheet 平衡表
A1: 年份 | B1: 需求(EB) | C1: 供给(EB) | D1: 缺口/需求
A2: 2025 | B2: =SUMIF(需求!A2:A43,A2,需求!F2:F43)/1000 | C2: =SUMIF(供给!A2:A10,A2,供给!F2:F10)/1000 | D2: =(C2-B2)/B2
A3: 2026 | B3: =SUMIF(需求!A2:A43,A3,需求!F2:F43)/1000 | C3: =SUMIF(供给!A2:A10,A3,供给!F2:F10)/1000 | D3: =(C3-B3)/B3
A4: 2027 | B4: =SUMIF(需求!A2:A43,A4,需求!F2:F43)/1000 | C4: =SUMIF(供给!A2:A10,A4,供给!F2:F10)/1000 | D4: =(C4-B4)/B4

Sheet 校准
A1: 项目 | B1: 本模型 | C1: 外部口径 | D1: 来源
A2: 2025 产量 | B2: 2.67 | C2: 2.63 | D2: iM 证券 2026-06（源65）
A3: 2026 产量 | B3: 4.36 | C3: 4.44 | D3: iM 证券 2026-06（源65）
A4: 2026 需求 | B4: 3.84 | C4: 4.23（iM）/ >3.75（TrendForce 2025-05） | D4: iM 证券（源65）/ TrendForce（源37）
A5: 2027 供给增速 | B5: +35% | C5: +45–50% | D5: KGI（源55）

Sheet 中国账本
A1: 中国账本：国产加速卡能用上的裸 HBM（EB）。中国账本只算"国产加速卡能用上的裸 HBM"：英伟达对华芯片自带 HBM，不在这本账里（2026 年 H200 进入大陆只有约 2 万颗 [源84]）。全球账本相应不再计长鑫产能，两本账不重复。
A2: 年份 | B2: 需求卡数(M) | C2: 每卡GB | D2: 不缺货需求 | E2: 机构出货口径需求 | F2: 期初库存 | G2: 合法进口 | H2: 灰色渠道 | I2: 长鑫 | J2: 武汉新芯 | K2: 可用合计 | L2: 覆盖率 | M2: 覆盖率(出货口径)
A3: 2024 | B3: 0.8 | C3: 64 | D3: 0.0512 | E3: 0.0512 | F3: 0 | G3: 0.182 | H3: 0.026 | I3: 0 | J3: 0 | K3: 0.208 | L3: 4.062 | M3: 4.062
A4: 2025 | B4: 1.3 | C4: 96 | D4: 0.1248 | E4: 0.1248 | F4: 0.1568 | G4: 0 | H4: 0.024 | I4: 0.0045 | J4: 0.0004 | K4: 0.1857 | L4: 1.488 | M4: 1.488
A5: 2026 | B5: 4.25 | C5: 100 | D5: 0.425 | E5: 0.155 | F5: 0.0609 | G5: 0 | H5: 0.01 | I5: 0.0315 | J5: 0.0032 | K5: 0.1056 | L5: 0.248 | M5: 0.681
A6: 2027 | B6: 5.25 | C6: 150 | D6: 0.7875 | E6: 0.2985 | F6: 0 | G6: 0 | H6: 0.01 | I6: 0.0842 | J6: 0.0084 | K6: 0.1026 | L6: 0.13 | M6: 0.344
A7: 假设见网页底稿第 3/4/5 步中国块；全部为估或机构口径，非官方数据。

Sheet 来源
A1: 编号 | B1: 说明 | C1: 链接
A2: 1 | B2: TrendForce：HBM 投片/位元占比、2027 合约价 | C2: https://www.trendforce.com/presscenter/news/20260602-13074.html
A3: 2 | B3: TrendForce HBM 3Q26 报告摘要 | C3: https://www.trendforce.com/research/download/RP260805KC3
A4: 3 | B4: TrendForce HBM 价格展望摘要 | C4: https://www.trendforce.com/research/download/RP260527UC
A5: 4 | B5: SK 海力士 2Q26 财报 | C5: https://news.skhynix.com/en/q2-2026-business-results/
A6: 5 | B6: 首尔经济：海力士财报会（HBM4 良率） | C6: https://en.sedaily.com/finance/2026/07/29/sk-hynix-ramps-up-hbm4-in-second-half-to-boost-record-763
A7: 6 | B7: 美光 FQ4 2026 财报 | C7: https://investors.micron.com/news/press-release/2026/Micron-Technology-Inc--Reports-Record-Fiscal-Fourth-Quarter-and-Full-Year-2026-Results/default.aspx
A8: 7 | B8: TrendForce 转 ETNews/Chosun：美光 10 万片、三星 15 万片 | C8: https://www.trendforce.com/news/2026/09/04/news-micron-reportedly-to-add-60k-hbm-wafersm-reaching-100k-by-year-end-to-narrow-gap-with-samsung-sk-hynix/
A9: 8 | B9: BigGo：三星 18 万 → 25 万片、base die 路线 | C9: https://finance.biggo.com/news/a6fce0cd-0fa5-463a-843d-d450cb21504a
A10: 9 | B10: Silicon Analysts：良率才是瓶颈、3 倍耗片 | C10: https://siliconanalysts.com/analysis/hbm4-capacity-bottleneck-2026-samsung-sk-hynix-qual
A11: 10 | B11: 三星 3Q26 业绩指引 | C11: https://news.samsung.com/global/samsung-electronics-announces-earnings-guidance-for-third-quarter-2026
A12: 11 | B12: Counterpoint HBM 份额 | C12: https://counterpointresearch.com/en/insights/global-dram-and-hbm-market-share
A13: 12 | B13: TrendForce 转经济日报：CoWoS 产能 | C13: https://www.trendforce.com/news/2026/06/15/news-tsmc-cowos-supply-demand-gap-reportedly-seen-narrowing-from-20-to-10-by-end-2026-as-capacity-expands/
... A102: 101 | B102: NoCut News 2026-10：存储"售罄到 2028 年"；美光 CEO Mehrotra 称 2027、2028 年需求都将超过供给；TrendForce 称新产能 2028 年才实质放量 | C102: https://en.nocutnews.co.kr/news/6586071

Sheet TOC约束
A1: 单位：百万颗 AI 加速器封装/季；算法见 toc.js / data/toc.json；除 CoWoS、HBM 外各环节规模为估计（含校准）；由 cowos/build.py 生成
A2: 季度 | B2: 需求 | C2: CoWoS | D2: 硅中介层 | E2: HBM | F2: TC键合机 | G2: ABF载板 | H2: 电力 | I2: 最小环节 | J2: 约束 | K2: 通过量
A3: 2024Q1 | B3: 1.917 | C3: 1.341 | D3: 1.646 | E3: 1.47 | F3: 3.274 | G3: 2.109 | H3: 2.517 | I3: CoWoS | J3: CoWoS | K3: 1.341
A4: 2024Q2 | B4: 2.091 | C4: 1.779 | D4: 2.127 | E4: 1.79 | F4: 4.097 | G4: 2.3 | H4: 2.517 | I4: CoWoS | J4: CoWoS | K4: 1.779
A5: 2024Q3 | B5: 2.266 | C5: 2.217 | D5: 2.609 | E5: 2.749 | F5: 4.92 | G5: 2.492 | H5: 2.768 | I5: CoWoS | J5: CoWoS | K5: 2.217
A6: 2024Q4 | B6: 2.44 | C6: 2.655 | D6: 3.082 | E6: 3.58 | F6: 5.743 | G6: 2.684 | H6: 2.768 | I6: CoWoS | J6: 需求（各环节都够） | K6: 2.44
A7: 2025Q1 | B7: 2.559 | C7: 2.331 | D7: 3.214 | E7: 3.377 | F7: 3.714 | G7: 2.687 | H7: 3.07 | I7: CoWoS | J7: CoWoS | K7: 2.331
A8: 2025Q2 | B8: 2.791 | C8: 2.961 | D8: 3.302 | E8: 3.678 | F8: 4.455 | G8: 2.931 | H8: 3.07 | I8: ABF 载板 | J8: 需求（各环节都够） | K8: 2.791
A9: 2025Q3 | B9: 3.024 | C9: 3.591 | D9: 3.391 | E9: 3.978 | F9: 5.196 | G9: 3.175 | H9: 3.93 | I9: ABF 载板 | J9: 需求（各环节都够） | K9: 3.024
A10: 2025Q4 | B10: 3.256 | C10: 4.221 | D10: 3.479 | E10: 4.281 | F10: 5.937 | G10: 3.419 | H10: 3.93 | I10: ABF 载板 | J10: 需求（各环节都够） | K10: 3.256
A11: 2026Q1 | B11: 4.349 | C11: 4.457 | D11: 4.722 | E11: 5.11 | F11: 7.275 | G11: 4.48 | H11: 6.755 | I11: CoWoS | J11: 需求（各环节都够） | K11: 4.349
A12: 2026Q2 | B12: 4.745 | C12: 5.211 | D12: 5.215 | E12: 5.445 | F12: 8.313 | G12: 4.887 | H12: 6.755 | I12: ABF 载板 | J12: 需求（各环节都够） | K12: 4.745
A13: 2026Q3 | B13: 5.14 | C13: 5.964 | D13: 5.709 | E13: 5.781 | F13: 9.35 | G13: 5.294 | H13: 7.025 | I13: ABF 载板 | J13: 需求（各环节都够） | K13: 5.14
A14: 2026Q4 | B14: 5.535 | C14: 6.718 | D14: 6.203 | E14: 6.118 | F14: 10.388 | G14: 5.701 | H14: 7.025 | I14: ABF 载板 | J14: 需求（各环节都够） | K14: 5.535
... A18: 2027Q4 | B18: 10.22 | C18: 10.932 | D18: 10.448 | E18: 9.131 | F18: 16.647 | G18: 7.269 | H18: 10.126 | I18: ABF 载板 | J18: ABF 载板 | K18: 7.269
